oppapi/__init__.py
oppapi/py.typed
oppapi-0.0.6.dist-info/LICENSE
oppapi-0.0.6.dist-info/WHEEL
oppapi-0.0.6.dist-info/METADATA
oppapi-0.0.6.dist-info/RECORD
